codes/brg.v
//BAUD RATE GENERATOR MODULE

module brg #(parameter CLOCK_FREQ = 100000000,
             parameter BAUD_RATE = 9600)(
             input clk,
             input reset,
             output reg baud_tick);

    localparam integer DIVISOR = CLOCK_FREQ/BAUD_RATE;
    localparam integer COUNTER_WIDTH = $clog2(DIVISOR);

    reg [COUNTER_WIDTH-1 : 0] count; //For counting to acknowledge baud tick

    always @(posedge clk) begin

        if(reset) begin

            count <= 'd0;
            baud_tick <= 1'b0;
        end

        else begin

            if(count == DIVISOR-1) begin //If condition for one baud tick is met

                count <= 'd0;
                baud_tick <= 1'b1;
            end
            else begin

                count <= count + 'd1;
                baud_tick <= 1'b0;
            end
        end
    end

endmodule

tb/brg_tb.v
//BAUD RATE GENERATOR TB
module test;

reg clk;
reg reset;

wire baud_tick;

brg #(.CLOCK_FREQ(100),
      .BAUD_RATE(10)) DUT(
      .clk(clk),
      .reset(reset),
      .baud_tick(baud_tick));

    always #5 clk = ~clk;

    initial begin

        $dumpfile("dump_brg.vcd");
        $dumpvars(0, test);

        clk = 1'b0;
        reset = 1'b1;
        #20;

        reset = 1'b0;
        #300;

        $finish;
    end

endmodule

simulation/dump_brg.vcd
$date
	Mon Jun 29 19:57:42 2026
$end
$version
	Icarus Verilog
$end
$timescale
	1s
$end
$scope module test $end
$var wire 1 ! baud_tick $end
$var reg 1 " clk $end
$var reg 1 # reset $end
$scope module DUT $end
$var wire 1 " clk $end
$var wire 1 # reset $end
$var parameter 32 $ BAUD_RATE $end
$var parameter 32 % CLOCK_FREQ $end
$var parameter 32 & COUNTER_WIDTH $end
$var parameter 32 ' DIVISOR $end
$var reg 1 ! baud_tick $end
$var reg 4 ( count [3:0] $end
$upscope $end
$upscope $end
$enddefinitions $end
$comment Show the parameter values. $end
$dumpall
b1010 '
b100 &
b1100100 %
b1010 $
$end
#0
$dumpvars
bx (
1#
0"
x!
$end
#5
0!
b0 (
1"
#10
0"
#15
1"
#20
0"
0#
#25
b1 (
1"
#30
0"
#35
b10 (
1"
#40
0"
#45
b11 (
1"
#50
0"
#55
b100 (
1"
#60
0"
#65
b101 (
1"
#70
0"
#75
b110 (
1"
#80
0"
#85
b111 (
1"
#90
0"
#95
b1000 (
1"
#100
0"
#105
b1001 (
1"
#110
0"
#115
b0 (
1!
1"
#120
0"
#125
b1 (
0!
1"
#130
0"
#135
b10 (
1"
#140
0"
#145
b11 (
1"
#150
0"
#155
b100 (
1"
#160
0"
#165
b101 (
1"
#170
0"
#175
b110 (
1"
#180
0"
#185
b111 (
1"
#190
0"
#195
b1000 (
1"
#200
0"
#205
b1001 (
1"
#210
0"
#215
b0 (
1!
1"
#220
0"
#225
b1 (
0!
1"
#230
0"
#235
b10 (
1"
#240
0"
#245
b11 (
1"
#250
0"
#255
b100 (
1"
#260
0"
#265
b101 (
1"
#270
0"
#275
b110 (
1"
#280
0"
#285
b111 (
1"
#290
0"
#295
b1000 (
1"
#300
0"
#305
b1001 (
1"
#310
0"
#315
b0 (
1!
1"
